py_multiapi/__init__.py
py_multiapi/main.py
py_multiapi-17.dist-info/LICENSE
py_multiapi-17.dist-info/METADATA
py_multiapi-17.dist-info/WHEEL
py_multiapi-17.dist-info/top_level.txt
py_multiapi-17.dist-info/RECORD
