Metadata-Version: 2.1
Name: py-multiapi
Version: 17
Summary: A Python Wrapper for api.itayki.com
Home-page: https://github.com/iiiiii1wepfj/py_multiapi
Author: Itay K
Author-email: itayki98@gmail.com
License: UNKNOWN
Download-URL: https://github.com/iiiiii1wepfj/py_multiapi/archive/refs/tags/v17.tar.gz
Project-URL: Documentation, https://api.itayki.com/docs
Project-URL: Source, https://github.com/iiiiii1wepfj/py_multiapi
Platform: UNKNOWN
Classifier: Programming Language :: Python :: 3
Classifier: License :: OSI Approved :: MIT License
Classifier: Operating System :: OS Independent
Requires-Python: >=3.6
License-File: LICENSE
Requires-Dist: httpx[http2]
